zipcode_coordinates_tz-0.4.0.dist-info/METADATA
zipcode_coordinates_tz-0.4.0.dist-info/WHEEL
zipcode_coordinates_tz-0.4.0.dist-info/entry_points.txt
zipcode_coordinates_tz-0.4.0.dist-info/licenses/LICENSE
zipcode_coordinates_tz/__init__.py
zipcode_coordinates_tz/__main__.py
zipcode_coordinates_tz/census.py
zipcode_coordinates_tz/commands/__init__.py
zipcode_coordinates_tz/commands/common.py
zipcode_coordinates_tz/commands/save.py
zipcode_coordinates_tz/constants.py
zipcode_coordinates_tz/http.py
zipcode_coordinates_tz/models.py
zipcode_coordinates_tz/postal.py
zipcode_coordinates_tz/py.typed
zipcode_coordinates_tz/timezone.py
zipcode_coordinates_tz/utils.py
zipcode_coordinates_tz-0.4.0.dist-info/RECORD
