Metadata-Version: 2.1
Name: zipcode-coordinates-tz
Version: 0.4.0
Summary: A Python package for querying US Zipcodes, and converting to coordinates and timezones
Keywords: geolocation,zipcodes,census,timezone,timezone-converter,postal-codes,pytz,usps
Author-Email: Robert Colfin <robert.m.colfin@gmail.com>
License: Apache
Classifier: Development Status :: 4 - Beta
Classifier: Intended Audience :: Developers
Classifier: License :: OSI Approved :: Apache Software License
Classifier: Natural Language :: English
Classifier: Operating System :: OS Independent
Classifier: Programming Language :: Python :: 3.9
Classifier: Programming Language :: Python :: 3.10
Classifier: Programming Language :: Python :: 3.11
Classifier: Programming Language :: Python :: 3.12
Classifier: Programming Language :: Python :: 3.13
Project-URL: homepage, https://github.com/rcolfin/zipcode-coordinates-tz
Requires-Python: <4.0,>=3.9
Requires-Dist: aiofiles<25.0.0,>=24.1.0
Requires-Dist: asyncclick<9.0.0.0,>=8.1.7.2
Requires-Dist: backoff<3.0.0,>=2.2.1
Requires-Dist: curl-cffi>=0.13.0
Requires-Dist: openpyxl<4.0.0,>=3.1.5
Requires-Dist: pytz<2026.0,>=2024.2
Requires-Dist: timezonefinder<8.0.0,>=6.5.7
Requires-Dist: xlrd<3.0.0,>=2.0.1
Requires-Dist: pandas>=1
